qualia_flow/__init__.py
qualia_flow/cli.py
qualia_flow/env_utils.py
qualia_flow/explorer.py
qualia_flow/generator.py
qualia_flow-0.1.1.dist-info/METADATA
qualia_flow-0.1.1.dist-info/WHEEL
qualia_flow-0.1.1.dist-info/entry_points.txt
qualia_flow-0.1.1.dist-info/RECORD
