Metadata-Version: 2.4
Name: qualia-flow
Version: 0.1.1
Summary: MLflow experiment exploration and notebook generation toolkit
Requires-Python: >=3.12
Requires-Dist: jupyter>=1.0.0
Requires-Dist: mlflow>=2.0.0
Requires-Dist: pandas>=2.0.0
Provides-Extra: dev
Requires-Dist: black>=23.0.0; extra == 'dev'
Requires-Dist: isort>=5.0.0; extra == 'dev'
Requires-Dist: pytest>=7.0.0; extra == 'dev'
